x_dgcnn/__init__.py
x_dgcnn/dgcnn.py
x_dgcnn/route.py
x_dgcnn-0.3.0.dist-info/LICENSE
x_dgcnn-0.3.0.dist-info/METADATA
x_dgcnn-0.3.0.dist-info/WHEEL
x_dgcnn-0.3.0.dist-info/top_level.txt
x_dgcnn-0.3.0.dist-info/RECORD
