Metadata-Version: 2.1
Name: x-dgcnn
Version: 0.3.0
Summary: X-DGCNN - Pytorch
Home-page: https://github.com/kentechx/x-dgcnn
Author: Kaidi Shen
License: MIT
Keywords: 3D segmentation,3D classification,point cloud understanding
Classifier: Development Status :: 4 - Beta
Classifier: Intended Audience :: Developers
Classifier: Topic :: Scientific/Engineering :: Artificial Intelligence
Classifier: License :: OSI Approved :: MIT License
Classifier: Programming Language :: Python :: 3.6
License-File: LICENSE
Requires-Dist: torch (>=1.10)
Requires-Dist: einops (>=0.6.1)
Requires-Dist: pykeops (>=2.1.2)
